telegram_uploader/__init__.py
telegram_uploader/_compat.py
telegram_uploader/api.py
telegram_uploader/caption_formatter.py
telegram_uploader/cli.py
telegram_uploader/config.py
telegram_uploader/download_files.py
telegram_uploader/exceptions.py
telegram_uploader/management.py
telegram_uploader/upload_files.py
telegram_uploader/utils.py
telegram_uploader/video.py
telegram_uploader/client/__init__.py
telegram_uploader/client/progress_bar.py
telegram_uploader/client/telegram_download_client.py
telegram_uploader/client/telegram_manager_client.py
telegram_uploader/client/telegram_upload_client.py
tests/__init__.py
tests/_compat.py
tests/test_caption_formatter.py
tests/test_cli.py
tests/test_config.py
tests/test_download_files.py
tests/test_exceptions.py
tests/test_files.py
tests/test_management.py
tests/test_upload_files.py
tests/test_utils.py
tests/test_video.py
tests/test_client/__init__.py
tests/test_client/test_progress_bar.py
tests/test_client/test_telegram_download_client.py
tests/test_client/test_telegram_manager_client.py
tests/test_client/test_telegram_upload_client.py
telegram_uploader-0.9.3.dist-info/AUTHORS.rst
telegram_uploader-0.9.3.dist-info/LICENSE
telegram_uploader-0.9.3.dist-info/METADATA
telegram_uploader-0.9.3.dist-info/WHEEL
telegram_uploader-0.9.3.dist-info/entry_points.txt
telegram_uploader-0.9.3.dist-info/top_level.txt
telegram_uploader-0.9.3.dist-info/RECORD
