Metadata-Version: 2.1
Name: telegram-uploader
Version: 0.9.3
Summary: A simple tool for interacting with the Telegram API, enabling file uploads (2GB), downloads, message deletion, and other common tasks. Built for automation and easy management of Telegram account activities. 
Home-page: https://github.com/mohammadham/telegram-uploader/
Download-URL: https://github.com/mohammadham/telegram-uploader/archive/master.zip
Author: MohammadHam
Author-email: contacto@MohammadHam.ir
Keywords: telegram-uploader,telegram-upload,telegram,upload,video
Platform: linux
Classifier: License :: OSI Approved :: MIT License
Classifier: Programming Language :: Python :: 3 :: Only
Classifier: Programming Language :: Python :: 3.11
Classifier: Programming Language :: Python :: 3.10
Classifier: Programming Language :: Python :: 3.7
Classifier: Programming Language :: Python :: 3.8
Classifier: Programming Language :: Python :: 3.9
Classifier: Operating System :: POSIX
Classifier: Operating System :: POSIX :: Linux
Classifier: Natural Language :: English
Classifier: Development Status :: 5 - Production/Stable
Provides: telegram_uploader
Provides: tests
License-File: LICENSE
License-File: AUTHORS.rst
Requires-Dist: telethon
Requires-Dist: click>=6.0
Requires-Dist: cryptg
Requires-Dist: hachoir
Requires-Dist: prompt-toolkit
Requires-Dist: pysocks
Requires-Dist: more-itertools
Requires-Dist: scandir; python_version < "3.6"
